tiff_crop_gui/__init__.py
tiff_crop_gui-1.0.6.dist-info/entry_points.txt
tiff_crop_gui-1.0.6.dist-info/WHEEL
tiff_crop_gui-1.0.6.dist-info/METADATA
tiff_crop_gui-1.0.6.dist-info/RECORD
