Metadata-Version: 2.1
Name: tiff_crop_gui
Version: 1.0.6
Summary: Automatically crops a directory of python files.
Requires-Dist: dearpygui
Requires-Dist: tqdm
Requires-Dist: Pillow
Requires-Dist: numpy
